[
    {
        "place_id": "ChIJA_6DxLJpdTERTt_7PgnNiQ8",
        "name": "Can Gio Coffee",
        "description": null,
        "is_spending_on_ads": false,
        "reviews": 494,
        "competitors": [
            {
                "name": "Gio long coffee",
                "link": "https://www.google.com/maps/search/Gi%C3%B3+l%E1%BB%99ng+coffee/@10.4051068,106.9661687?authuser=0&hl=en&entry=ttu",
                "reviews": 173,
                "rating": 4.4,
                "main_category": "Coffee shop"
            },
            {
                "name": "Goc Coffee & Juice Bar",
                "link": "https://www.google.com/maps/search/G%C3%B3c+Coffee+%26+Juice+Bar/@10.410658,106.96978560000001?authuser=0&hl=en&entry=ttu",
                "reviews": 94,
                "rating": 4.8,
                "main_category": "Coffee shop"
            },
            {
                "name": "Cafe Do Phu",
                "link": "https://www.google.com/maps/search/Cafe+%C4%90%E1%BB%97+Ph%E1%BB%A7/@10.405080199999999,106.96607?authuser=0&hl=en&entry=ttu",
                "reviews": 70,
                "rating": 4.2,
                "main_category": "Cafe"
            },
            {
                "name": "Mangrove Coffee Can Gio",
                "link": "https://www.google.com/maps/search/Mangrove+Coffee+C%E1%BA%A7n+Gi%E1%BB%9D/@10.388079,106.919248?authuser=0&hl=en&entry=ttu",
                "reviews": 8,
                "rating": 3.5,
                "main_category": "Coffee shop"
            },
            {
                "name": "Cafe vong",
                "link": "https://www.google.com/maps/search/Cafe+v%C3%B5ng/@10.395466700000002,106.9175331?authuser=0&hl=en&entry=ttu",
                "reviews": 6,
                "rating": 4.5,
                "main_category": "Cafe"
            }
        ],
        "website": "https://www.facebook.com/groups/467390918602314/%3Fref%3Dshare%26mibextid%3DNSMWBT",
        "owner": {
            "id": "115153770544087397479",
            "name": "Can Gio Coffee (Owner)",
            "link": "https://www.google.com/maps/contrib/115153770544087397479"
        },
        "featured_image": "https://lh5.googleusercontent.com/p/AF1QipP7j0k3OOGpLFY6T6A4Xk_5AIDJEV8wbQI12qV-=w408-h306-k-no",
        "main_category": "Coffee shop",
        "categories": [
            "Coffee shop"
        ],
        "rating": 4.5,
        "workday_timing": "6:30 AM-9 PM",
        "closed_on": "Open All Days",
        "phone": "+84 976 989 739",
        "address": "Can Gio Coffee, 802 Duyen Hai, Long Hoa, Can Gio, Thanh pho Ho Chi Minh, Vietnam",
        "review_keywords": [
            {
                "keyword": "garden",
                "count": 3
            }
        ],
        "link": "https://www.google.com/maps/place/C%E1%BA%A7n+Gi%E1%BB%9D+Coffee/data=!4m7!3m6!1s0x317569b2c483fe03:0xf89cd093efbdf4e!8m2!3d10.3956684!4d106.9187777!16s%2Fg%2F11hz38ftcc!19sChIJA_6DxLJpdTERTt_7PgnNiQ8?authuser=0&hl=en&rclk=1"
    },
    {
        "place_id": "ChIJuwxIQqhpdTERoI2Hew67fDk",
        "name": "Goc Coffee & Juice Bar",
        "description": null,
        "is_spending_on_ads": false,
        "reviews": 94,
        "competitors": [
            {
                "name": "Can Gio Coffee",
                "link": "https://www.google.com/maps/search/C%E1%BA%A7n+Gi%E1%BB%9D+Coffee/@10.3956684,106.91877769999999?authuser=0&hl=en&entry=ttu",
                "reviews": 493,
                "rating": 4.5,
                "main_category": "Coffee shop"
            },
            {
                "name": "Gio long coffee",
                "link": "https://www.google.com/maps/search/Gi%C3%B3+l%E1%BB%99ng+coffee/@10.4051068,106.9661687?authuser=0&hl=en&entry=ttu",
                "reviews": 173,
                "rating": 4.4,
                "main_category": "Coffee shop"
            },
            {
                "name": "Cafe Ganh Hao",
                "link": "https://www.google.com/maps/search/Cafe+Ganh+Hao/@10.412391999999999,106.963634?authuser=0&hl=en&entry=ttu",
                "reviews": 153,
                "rating": 4,
                "main_category": "Cafe"
            },
            {
                "name": "Cafe Do Phu",
                "link": "https://www.google.com/maps/search/Cafe+%C4%90%E1%BB%97+Ph%E1%BB%A7/@10.405080199999999,106.96607?authuser=0&hl=en&entry=ttu",
                "reviews": 70,
                "rating": 4.2,
                "main_category": "Cafe"
            },
            {
                "name": "Cafe Vong - Co Tuong Binh Hoa",
                "link": "https://www.google.com/maps/search/Cafe+V%C3%B5ng+-+C%E1%BB%9D+T%C6%B0%E1%BB%9Bng+B%C3%ACnh+Hoa/@10.4107262,106.9719056?authuser=0&hl=en&entry=ttu",
                "reviews": 11,
                "rating": 4.5,
                "main_category": "Cafe"
            }
        ],
        "website": null,
        "owner": {
            "id": "100088110277185347934",
            "name": "Goc Coffee & Juice Bar (Owner)",
            "link": "https://www.google.com/maps/contrib/100088110277185347934"
        },
        "featured_image": "https://lh5.googleusercontent.com/p/AF1QipOCRHvI6EoTydpmxAHtGOo31ZlHXF1fwxGeB7sa=w408-h306-k-no",
        "main_category": "Coffee shop",
        "categories": [
            "Coffee shop"
        ],
        "rating": 4.8,
        "workday_timing": "7 AM-10 PM",
        "closed_on": "Open All Days",
        "phone": "+84 828 263 249",
        "address": "Goc Coffee & Juice Bar, 117 Dang van Kieu, TT. Can Thanh, Can Gio, Thanh pho Ho Chi Minh, Vietnam",
        "review_keywords": [],
        "link": "https://www.google.com/maps/place/G%C3%B3c+Coffee+%26+Juice+Bar/data=!4m7!3m6!1s0x317569a842480cbb:0x397cbb0e7b878da0!8m2!3d10.410658!4d106.9697856!16s%2Fg%2F11qrfk9tqq!19sChIJuwxIQqhpdTERoI2Hew67fDk?authuser=0&hl=en&rclk=1"
    },
    {
        "place_id": "ChIJvQLyA3FpdTER6NqdCC71aHM",
        "name": "Can Gio Port Cafe",
        "description": null,
        "is_spending_on_ads": false,
        "reviews": 7,
        "competitors": [
            {
                "name": "Can Gio Coffee",
                "link": "https://www.google.com/maps/search/C%E1%BA%A7n+Gi%E1%BB%9D+Coffee/@10.3956684,106.91877769999999?authuser=0&hl=en&entry=ttu",
                "reviews": 493,
                "rating": 4.5,
                "main_category": "Coffee shop"
            },
            {
                "name": "Goc Coffee & Juice Bar",
                "link": "https://www.google.com/maps/search/G%C3%B3c+Coffee+%26+Juice+Bar/@10.410658,106.96978560000001?authuser=0&hl=en&entry=ttu",
                "reviews": 94,
                "rating": 4.8,
                "main_category": "Coffee shop"
            },
            {
                "name": "Cafe THINH",
                "link": "https://www.google.com/maps/search/Cafe+TH%E1%BB%8ANH/@10.4137118,106.97294009999999?authuser=0&hl=en&entry=ttu",
                "reviews": 51,
                "rating": 4.3,
                "main_category": "Cafe"
            },
            {
                "name": "Cafe Vong - Co Tuong Binh Hoa",
                "link": "https://www.google.com/maps/search/Cafe+V%C3%B5ng+-+C%E1%BB%9D+T%C6%B0%E1%BB%9Bng+B%C3%ACnh+Hoa/@10.4107262,106.9719056?authuser=0&hl=en&entry=ttu",
                "reviews": 11,
                "rating": 4.5,
                "main_category": "Cafe"
            }
        ],
        "website": null,
        "owner": {
            "id": null,
            "name": "Can Gio Port Cafe (Owner)",
            "link": null
        },
        "featured_image": "https://lh5.googleusercontent.com/p/AF1QipPsAp15pYthl1RfoIMQh2UemcV7HHNPhEwyFj18=w493-h240-k-no",
        "main_category": "Cafe",
        "categories": [
            "Cafe"
        ],
        "rating": 3.9,
        "workday_timing": null,
        "closed_on": "Open All Days",
        "phone": null,
        "address": "Can Gio Port Cafe, 2B Dang van Kieu, TT. Can Thanh, Can Gio, Thanh pho Ho Chi Minh, Vietnam",
        "review_keywords": [],
        "link": "https://www.google.com/maps/place/Can+Gio+Port+Cafe/data=!4m7!3m6!1s0x3175697103f202bd:0x7368f52e089ddae8!8m2!3d10.4130166!4d106.9678815!16s%2Fg%2F11g6px7q3z!19sChIJvQLyA3FpdTER6NqdCC71aHM?authuser=0&hl=en&rclk=1"
    },
    {
        "place_id": "ChIJnzg-HZtpdTERNe7vZbDRlas",
        "name": "Coffee Trung Can Gio",
        "description": null,
        "is_spending_on_ads": false,
        "reviews": 1,
        "competitors": [
            {
                "name": "Can Gio Coffee",
                "link": "https://www.google.com/maps/search/C%E1%BA%A7n+Gi%E1%BB%9D+Coffee/@10.3956684,106.91877769999999?authuser=0&hl=en&entry=ttu",
                "reviews": 493,
                "rating": 4.5,
                "main_category": "Coffee shop"
            },
            {
                "name": "Coffee Goc Pho",
                "link": "https://www.google.com/maps/search/Coffee+Goc+Pho/@10.403908699999999,106.9589312?authuser=0&hl=en&entry=ttu",
                "reviews": 89,
                "rating": 4.1,
                "main_category": "Cafe"
            },
            {
                "name": "Cafe vong",
                "link": "https://www.google.com/maps/search/Cafe+v%C3%B5ng/@10.395466700000002,106.9175331?authuser=0&hl=en&entry=ttu",
                "reviews": 6,
                "rating": 4.5,
                "main_category": "Cafe"
            },
            {
                "name": "479 Coffee",
                "link": "https://www.google.com/maps/search/479+Coffee/@10.4025382,106.953598?authuser=0&hl=en&entry=ttu",
                "reviews": 4,
                "rating": 5,
                "main_category": "Cafe"
            }
        ],
        "website": null,
        "owner": {
            "id": null,
            "name": "Coffee Trung Can Gio (Owner)",
            "link": null
        },
        "featured_image": "https://lh5.googleusercontent.com/p/AF1QipOx9KPCoanjXQeiFxwsY-byeBTmT7nplt_bgfE=w408-h544-k-no",
        "main_category": "Art cafe",
        "categories": [
            "Art cafe"
        ],
        "rating": 5,
        "workday_timing": null,
        "closed_on": "Open All Days",
        "phone": null,
        "address": "Coffee Trung Can Gio, Ba, 205 Duong Duyen Hai, KP. Mieu, Can Gio, Thanh pho Ho Chi Minh, Vietnam",
        "review_keywords": [],
        "link": "https://www.google.com/maps/place/Coffee+Trung+Can+Gio/data=!4m7!3m6!1s0x3175699b1d3e389f:0xab95d1b065efee35!8m2!3d10.4074719!4d106.9661595!16s%2Fg%2F11j33c_jvp!19sChIJnzg-HZtpdTERNe7vZbDRlas?authuser=0&hl=en&rclk=1"
    }
]